MANIFEST.in
README.md
requirements.txt
setup.cfg
setup.py
redtrics/__init__.py
redtrics.egg-info/PKG-INFO
redtrics.egg-info/SOURCES.txt
redtrics.egg-info/dependency_links.txt
redtrics.egg-info/entry_points.txt
redtrics.egg-info/pbr.json
redtrics.egg-info/requires.txt
redtrics.egg-info/top_level.txt
redtrics/api/__init__.py
redtrics/api/github.py
redtrics/api/influxdbapi.py
redtrics/cli/__init__.py
redtrics/cli/app.py
redtrics/core/__init__.py
redtrics/core/default_settings.py
redtrics/core/filters.py
redtrics/core/runner.py
redtrics/core/settings.py
redtrics/etc/logging.ini
redtrics/metrics/__init__.py
redtrics/metrics/base.py
redtrics/metrics/build_status.py
redtrics/metrics/gh_commits_last_week.py
redtrics/metrics/pr_stats.py
redtrics/metrics/registry.py
redtrics/templates/mail.html
redtrics/utils/__init__.py
redtrics/utils/dateutils.py
redtrics/utils/decorators.py