Metadata-Version: 1.1
Name: redtrics
Version: 1.0.1
Summary: Redtrics generates metrics about the use of Github by developers.
Home-page: http://github.com/RedMart/redtrics
Author: RedMart Ltd
Author-email: oss@redmart.com
License: MIT
Keywords: github metrics redmart commits size age
Platform: UNKNOWN
Classifier: Development Status :: 5 - Production/Stable
Classifier: Intended Audience :: Developers
Classifier: Topic :: Utilities
Classifier: Programming Language :: Python
Classifier: Programming Language :: Python :: 2
Classifier: Programming Language :: Python :: 2.6
Classifier: Programming Language :: Python :: 2.7
Classifier: Programming Language :: Python :: 3
Classifier: Programming Language :: Python :: 3.2
Classifier: Programming Language :: Python :: 3.3
Classifier: Programming Language :: Python :: 3.4
